simple_aws_wrapper/__init__.py
simple_aws_wrapper/config.py
simple_aws_wrapper/resource_manager.py
simple_aws_wrapper/const/__init__.py
simple_aws_wrapper/const/regions.py
simple_aws_wrapper/const/services.py
simple_aws_wrapper/exceptions/__init__.py
simple_aws_wrapper/exceptions/exceptions.py
simple_aws_wrapper/services/__init__.py
simple_aws_wrapper/services/aws_lambda.py
simple_aws_wrapper/services/dynamodb.py
simple_aws_wrapper/services/parameter_store.py
simple_aws_wrapper/services/s3.py
simple_aws_wrapper/services/secrets_manager.py
simple_aws_wrapper/services/sqs.py
simple_aws_wrapper-2.12.3.dist-info/LICENSE
simple_aws_wrapper-2.12.3.dist-info/METADATA
simple_aws_wrapper-2.12.3.dist-info/WHEEL
simple_aws_wrapper-2.12.3.dist-info/top_level.txt
simple_aws_wrapper-2.12.3.dist-info/RECORD
