Metadata-Version: 2.2
Name: simple_aws_wrapper
Version: 2.12.3
Summary: Implementazione minimale per la gestione delle risorse in cloud di AWS
Author-email: Andrea Trupia <andrea.trupia.96@gmail.com>
Project-URL: Homepage, https://github.com/AndreaTrupia/simple_aws_wrapper
Classifier: Programming Language :: Python :: 3
Classifier: License :: OSI Approved :: MIT License
Classifier: Operating System :: OS Independent
Requires-Python: >=3.10
License-File: LICENSE
